simple_dep_cache/__init__.py
simple_dep_cache/backends.py
simple_dep_cache/config.py
simple_dep_cache/context.py
simple_dep_cache/decorators.py
simple_dep_cache/events.py
simple_dep_cache/factories.py
simple_dep_cache/fakes.py
simple_dep_cache/manager.py
simple_dep_cache/redis_backends.py
simple_dep_cache/types.py
simple_dep_cache/utils.py
simple_dep_cache-0.2.1.dist-info/METADATA
simple_dep_cache-0.2.1.dist-info/WHEEL
simple_dep_cache-0.2.1.dist-info/RECORD
