Metadata-Version: 2.4
Name: simple-dep-cache
Version: 0.2.1
Summary: Redis-based caching library with intelligent dependency tracking for Python applications
Project-URL: Homepage, https://github.com/tintty1/simple-dep-cache
Project-URL: Repository, https://github.com/tintty1/simple-dep-cache
Project-URL: Documentation, https://github.com/tintty1/simple-dep-cache
License: MIT
Keywords: cache,cache invalidation,dependency,redis
Classifier: Intended Audience :: Developers
Classifier: License :: OSI Approved :: MIT License
Classifier: Programming Language :: Python :: 3
Classifier: Programming Language :: Python :: 3.10
Classifier: Programming Language :: Python :: 3.11
Classifier: Programming Language :: Python :: 3.12
Classifier: Topic :: Software Development :: Libraries :: Python Modules
Requires-Python: >=3.10
Requires-Dist: redis
Provides-Extra: fast-json
Requires-Dist: orjson; extra == 'fast-json'
